hammadpy_sm/__init__.py
hammadpy_sm/core/__init__.py
hammadpy_sm/core/core.py
hammadpy_sm/interactions/__init__.py
hammadpy_sm/interactions/inputs.py
hammadpy_sm/interactions/messages.py
hammadpy_sm/interactions/status.py
hammadpy_sm/interactions/verifiers.py
hammadpy_sm/open/__init__.py
hammadpy_sm/open/chat_openai.py
hammadpy_sm-1.0.0.dist-info/METADATA
hammadpy_sm-1.0.0.dist-info/WHEEL
hammadpy_sm-1.0.0.dist-info/top_level.txt
hammadpy_sm-1.0.0.dist-info/RECORD
