Metadata-Version: 2.1
Name: hammadpy_sm
Version: 1.0.0
Summary: Hammad's Python Library
Author: Hammad Saeed
Author-email: hammad@supportvectors.com
Classifier: Programming Language :: Python :: 3
Classifier: License :: OSI Approved :: MIT License
Classifier: Operating System :: OS Independent
Requires-Python: >3.10
Requires-Dist: anyio
Requires-Dist: attrs
Requires-Dist: certifi
Requires-Dist: charset-normalizer
Requires-Dist: click
Requires-Dist: colorama
Requires-Dist: distro
Requires-Dist: docstring-parser
Requires-Dist: frozenlist
Requires-Dist: h11
Requires-Dist: httpcore
Requires-Dist: httpx
Requires-Dist: idna
Requires-Dist: instructor
Requires-Dist: markdown-it-py
Requires-Dist: mdurl
Requires-Dist: multidict
Requires-Dist: openai
Requires-Dist: prompt-toolkit
Requires-Dist: pydantic
Requires-Dist: pydantic-core
Requires-Dist: Pygments
Requires-Dist: rfc3986
Requires-Dist: rich
Requires-Dist: sniffio
Requires-Dist: tenacity
Requires-Dist: tqdm
Requires-Dist: typer
Requires-Dist: typing-extensions
Requires-Dist: validus
Requires-Dist: wcwidth
Requires-Dist: yarl
